{
	"name": "CustPay",
	"properties": {
		"linkedServiceName": {
			"referenceName": "AzureBlobStorage1",
			"type": "LinkedServiceReference"
		},
		"parameters": {
			"root": {
				"type": "string"
			},
			"fname": {
				"type": "string"
			}
		},
		"annotations": [],
		"type": "DelimitedText",
		"typeProperties": {
			"location": {
				"type": "AzureBlobStorageLocation",
				"fileName": "custPay.csv",
				"folderPath": "Input",
				"container": "adfdemo"
			},
			"columnDelimiter": ",",
			"escapeChar": "\\",
			"firstRowAsHeader": true,
			"quoteChar": "\""
		},
		"schema": [
			{
				"name": "Customer name",
				"type": "String"
			},
			{
				"name": "Title",
				"type": "String"
			},
			{
				"name": "depid",
				"type": "String"
			},
			{
				"name": "salary",
				"type": "String"
			},
			{
				"name": "department",
				"type": "String"
			}
		]
	}
}